pulp_mia.py
PuLP_MiA-0.1.1.data/scripts/pulp_mia.py
PuLP_MiA-0.1.1.dist-info/LICENSE
PuLP_MiA-0.1.1.dist-info/METADATA
PuLP_MiA-0.1.1.dist-info/WHEEL
PuLP_MiA-0.1.1.dist-info/top_level.txt
PuLP_MiA-0.1.1.dist-info/RECORD
