Metadata-Version: 2.1
Name: PuLP-MiA
Version: 0.1.1
Summary: Multi-index Addon for PuLP
Home-page: https://github.com/Palich239/PuLP-MiA
Author: Dmitriy Pavlov
Author-email: dpavlov239@mail.ru
License: MIT
Keywords: Optimization,Linear Programming,Operations Research
Platform: any
Classifier: Development Status :: 3 - Alpha
Classifier: Intended Audience :: Science/Research
Classifier: Intended Audience :: Developers
Classifier: License :: OSI Approved :: MIT License
Classifier: Natural Language :: Russian
Classifier: Programming Language :: Python
Classifier: Topic :: Software Development :: Libraries :: Python Modules
Classifier: Topic :: Scientific/Engineering :: Mathematics
Classifier: Programming Language :: Python :: 3.4
Classifier: Programming Language :: Python :: 3.5
Classifier: Programming Language :: Python :: 3.6
Classifier: Programming Language :: Python :: 3.7
Classifier: Programming Language :: Python :: 3.8
Classifier: Programming Language :: Python :: 3.9
Requires-Dist: pulp (>=1.6.10)
Requires-Dist: amply (>=0.1.2)
